sherlock/.DS_Store
sherlock/.coverage
sherlock/__init__.py
sherlock/__version__.py
sherlock/advanced_settings.yaml
sherlock/catalogue_conesearch.py
sherlock/cl_utils.py
sherlock/database.py
sherlock/database_cleaner.py
sherlock/default_settings.yaml
sherlock/test_settings.yaml
sherlock/transient_catalogue_crossmatch.py
sherlock/transient_classifier.py
sherlock/utKit.py
sherlock/commonutils/.DS_Store
sherlock/commonutils/__init__.py
sherlock/commonutils/get_crossmatch_catalogues_column_map.py
sherlock/commonutils/getpackagepath.py
sherlock/commonutils/update_wiki_pages.py
sherlock/commonutils/tests/__init__.py
sherlock/commonutils/tests/test_get_crossmatch_catalogues_column_map.py
sherlock/commonutils/tests/test_update_wiki_pages.py
sherlock/commonutils/tests/input/.gitkeep
sherlock/commonutils/tests/output/.gitkeep
sherlock/imports/.DS_Store
sherlock/imports/__init__.py
sherlock/imports/_base_importer.py
sherlock/imports/ifs.py
sherlock/imports/ned.py
sherlock/imports/ned_d.py
sherlock/imports/veron.py
sherlock/imports/tests/__init__.py
sherlock/imports/tests/test_ifs.py
sherlock/imports/tests/test_ned.py
sherlock/imports/tests/test_ned_d.py
sherlock/imports/tests/test_veron.py
sherlock/imports/tests/input/milliquas-test-data.txt
sherlock/imports/tests/input/ned_d_test.csv
sherlock/imports/tests/input/veron-test-data.txt
sherlock/imports/tests/output/milliquas-test-data.txt
sherlock/imports/tests/output/ned_d_test.csv
sherlock/imports/tests/output/veron-test-data.txt
sherlock/resources/package.mplstyle
sherlock/tests/.DS_Store
sherlock/tests/__init__.py
sherlock/tests/test_catalogue_conesearch.py
sherlock/tests/test_cl_utils.py
sherlock/tests/test_database.py
sherlock/tests/test_database_cleaner.py
sherlock/tests/test_transient_catalogue_crossmatch.py
sherlock/tests/test_transient_classifier.py
sherlock/tests/input/.gitkeep
sherlock/tests/output/.gitkeep
sherlock/tests/resources/transient_database/repopulate_transient_database.sql
qub_sherlock-3.1.0.dist-info/LICENSE
qub_sherlock-3.1.0.dist-info/METADATA
qub_sherlock-3.1.0.dist-info/WHEEL
qub_sherlock-3.1.0.dist-info/entry_points.txt
qub_sherlock-3.1.0.dist-info/top_level.txt
qub_sherlock-3.1.0.dist-info/RECORD
