Metadata-Version: 2.2
Name: qub-sherlock
Version: 3.1.0
Summary: mine a library of historical and on-going astronomical survey data in an attempt to identify the sources of transient/variable events, and predict their classifications based on crossmatched data
Home-page: https://github.com/thespacedoctor/sherlock
Download-URL: https://github.com/thespacedoctor/sherlock/archive/v3.1.0.zip
Author: David Young
Author-email: davidrobertyoung@gmail.com
License: MIT
Keywords: astronomy, classification, crossmatch, sherlock, transient
Classifier: Development Status :: 4 - Beta
Classifier: License :: OSI Approved :: MIT License
Classifier: Programming Language :: Python :: 3.7
Classifier: Topic :: Utilities
License-File: LICENSE
Requires-Dist: pyyaml
Requires-Dist: qub-sherlock
Requires-Dist: fundamentals>=2.7.7
Requires-Dist: astrocalc>=0.4.6
Requires-Dist: neddy
Requires-Dist: HMpTy>=1.8.0
Requires-Dist: pymysql
Requires-Dist: psutil
Requires-Dist: sloancone
Requires-Dist: numpy
Requires-Dist: tabulate
Dynamic: author
Dynamic: author-email
Dynamic: classifier
Dynamic: description
Dynamic: description-content-type
Dynamic: download-url
Dynamic: home-page
Dynamic: keywords
Dynamic: license
Dynamic: requires-dist
Dynamic: summary
